qwiic_large_oled.py
sparkfun_qwiic_large_oled-0.0.1.dist-info/LICENSE
sparkfun_qwiic_large_oled-0.0.1.dist-info/METADATA
sparkfun_qwiic_large_oled-0.0.1.dist-info/WHEEL
sparkfun_qwiic_large_oled-0.0.1.dist-info/top_level.txt
sparkfun_qwiic_large_oled-0.0.1.dist-info/RECORD
